[{"f":"jzmlb7vfzgqe","t":"Bokep Indo Viral Gadis Smp Di Ajarin Ngewe Ayah Sendiri Sudah Ditungguin","si":"https://thumbcdn.com/snaps/lv013zskji2v3am0.jpg","sp":"https://thumbcdn.com/splash/lv013zskji2v3am0.jpg","d":1384,"vw":415987,"up":"2023-06-09 20:58:32","pe":"","pd":"https://myvidplay.com/d/jzmlb7vfzgqe","k":"Video Indo","src":"doodstream"},{"f":"1a2vvx4dwju6","t":"Bokep Bocil Smp Belajar Colmek Bacoltube Lulustream HD Terbaru Tiktok Skandal","si":"https://thumbcdn.com/snaps/nucfaz8wxbsxnlwf.jpg","sp":"https://thumbcdn.com/splash/nucfaz8wxbsxnlwf.jpg","d":131,"vw":174994,"up":"2023-11-23 18:58:07","pe":"","pd":"https://myvidplay.com/d/1a2vvx4dwju6","k":"Video Skandal","src":"doodstream"},{"f":"f7q08u7sq40l","t":"Cantik Gemoy Video Lulustream Skandal Viral Colmek","si":"https://thumbcdn.com/snaps/rsc5jya49aoasg75.jpg","sp":"https://thumbcdn.com/splash/rsc5jya49aoasg75.jpg","d":1547,"vw":62799,"up":"2023-04-18 21:30:51","pe":"","pd":"https://myvidplay.com/d/f7q08u7sq40l","k":"Video Skandal","src":"doodstream"},{"f":"u1hro3lsva69","t":"Wife Prank Ojol Tahun Baru SMA Bokep Terbaru Video Skandal","si":"https://thumbcdn.com/snaps/jp28x7zt66lryl5q.jpg","sp":"https://thumbcdn.com/splash/jp28x7zt66lryl5q.jpg","d":140,"vw":36286,"up":"2023-07-04 21:29:36","pe":"","pd":"https://myvidplay.com/d/u1hro3lsva69","k":"Video Skandal","src":"doodstream"},{"f":"maanltld14ue","t":"Mbah Maryono Ngentot Sama Pasiennya Yang Masih Abg Colmek Lulustream SMA Skandal","si":"https://thumbcdn.com/snaps/fwtc08tn5x8phole.jpg","sp":"https://thumbcdn.com/splash/fwtc08tn5x8phole.jpg","d":464,"vw":35740,"up":"2023-10-08 01:32:53","pe":"","pd":"https://myvidplay.com/d/maanltld14ue","k":"Video Skandal","src":"doodstream"},{"f":"ep3i1xrwp4um","t":"Bocil Some Sama Shemale Full Live Update Terbaru Tiktok","si":"https://thumbcdn.com/snaps/cul7aa3jahn9zxl2.jpg","sp":"https://thumbcdn.com/splash/cul7aa3jahn9zxl2.jpg","d":75,"vw":25779,"up":"2024-01-02 10:32:24","pe":"","pd":"https://myvidplay.com/d/ep3i1xrwp4um","k":"Video Viral","src":"doodstream"},{"f":"b5k5wwgkptg3","t":"Ms Breewc Cosplay Host Chindo Sangetube Viral Jilbab Video Terbaru Full","si":"https://thumbcdn.com/snaps/q2dgfu51jx0twy0j.jpg","sp":"https://thumbcdn.com/splash/q2dgfu51jx0twy0j.jpg","d":1171,"vw":20759,"up":"2023-07-26 21:00:48","pe":"","pd":"https://myvidplay.com/d/b5k5wwgkptg3","k":"Video Jilbab","src":"doodstream"},{"f":"0i99wu9jqcie","t":"Ukhti Abg Sma Sange Lulustream Skandal Terbaru Video","si":"https://thumbcdn.com/snaps/iwzqfyir0hp1gckz.jpg","sp":"https://thumbcdn.com/splash/iwzqfyir0hp1gckz.jpg","d":110,"vw":20494,"up":"2023-07-26 21:03:27","pe":"","pd":"https://myvidplay.com/d/0i99wu9jqcie","k":"Video Skandal","src":"doodstream"},{"f":"8yzhr9neybif","t":"Kebaya Coklat Yang Lagi Viral Sekarang Update Terbaru Tiktok Twitter","si":"https://thumbcdn.com/snaps/dgdvt93utnaa2jdv.jpg","sp":"https://thumbcdn.com/splash/dgdvt93utnaa2jdv.jpg","d":196,"vw":18476,"up":"2023-11-30 21:23:35","pe":"","pd":"https://myvidplay.com/d/8yzhr9neybif","k":"Video Viral","src":"doodstream"},{"f":"yu0yj836b55e","t":"Mbah Maryono Jilbab Hijau Ep Live SMA Update Bokep Colmek","si":"https://thumbcdn.com/snaps/drllxemvvz9i5z36.jpg","sp":"https://thumbcdn.com/splash/drllxemvvz9i5z36.jpg","d":884,"vw":17897,"up":"2023-10-08 02:46:40","pe":"","pd":"https://myvidplay.com/d/yu0yj836b55e","k":"Video Jilbab","src":"doodstream"},{"f":"kn0w63fiiigx","t":"Tante Maya Hijab Jepit Uting Colmek Sangetube Guru Tiktok Jilbab Indo Viral","si":"https://thumbcdn.com/snaps/7ptz1gppmcp9m98q.jpg","sp":"https://thumbcdn.com/splash/7ptz1gppmcp9m98q.jpg","d":440,"vw":16119,"up":"2023-07-26 21:01:54","pe":"","pd":"https://myvidplay.com/d/kn0w63fiiigx","k":"Video Jilbab","src":"doodstream"},{"f":"eongluc1vsc2","t":"Kenangan Saat Disepongin Kontol Oleh Mantan Pacar Viral Streaming Indo Live Twitter","si":"https://thumbcdn.com/snaps/rrtj7l24zqij9qa6.jpg","sp":"https://thumbcdn.com/splash/rrtj7l24zqij9qa6.jpg","d":133,"vw":13804,"up":"2023-07-02 20:25:06","pe":"","pd":"https://myvidplay.com/d/eongluc1vsc2","k":"Video Indo","src":"doodstream"},{"f":"ao8uul5nphr8","t":"Uno Kanaya Diperkosa Saat Yoga Video Tiktok Twitter Doodstream Update","si":"https://thumbcdn.com/snaps/7o4zyffqg2lobhxh.jpg","sp":"https://thumbcdn.com/splash/7o4zyffqg2lobhxh.jpg","d":1892,"vw":13054,"up":"2023-11-23 18:59:58","pe":"","pd":"https://myvidplay.com/d/ao8uul5nphr8","k":"Video Viral","src":"doodstream"},{"f":"otm1sa8ig14o","t":"Brondong Vs Tante Girang Yang Sangean Bokep Id Tiktok SMA Guru Colmek","si":"https://thumbcdn.com/snaps/r8wrrleebcobk5aw.jpg","sp":"https://thumbcdn.com/splash/r8wrrleebcobk5aw.jpg","d":1039,"vw":12460,"up":"2023-10-13 20:39:17","pe":"","pd":"https://myvidplay.com/d/otm1sa8ig14o","k":"Video Viral","src":"doodstream"},{"f":"7qndb2u34csn","t":"Bokep Viral Ayang Minta Jatah Dibelakang Rumah Video Update Tiktok Terbaru Guru","si":"https://thumbcdn.com/snaps/wb03ls9k7bgn57a4.jpg","sp":"https://thumbcdn.com/splash/wb03ls9k7bgn57a4.jpg","d":459,"vw":11588,"up":"2023-07-04 21:26:12","pe":"","pd":"https://myvidplay.com/d/7qndb2u34csn","k":"Video Viral","src":"doodstream"},{"f":"ltj6yznz8bc8","t":"Video Bokep Bebby Udah Gatel Di Mobil Pengen Ngewe Doodstream Dood Bond","si":"https://thumbcdn.com/snaps/ubdvqh52zt5eln5a.jpg","sp":"https://thumbcdn.com/splash/ubdvqh52zt5eln5a.jpg","d":199,"vw":8669,"up":"2023-07-10 11:46:11","pe":"","pd":"https://myvidplay.com/d/ltj6yznz8bc8","k":"Video Viral","src":"doodstream"},{"f":"0bime8ilvtgm","t":"Ayang Toket Bulet Goyangannya Nikmat Banget Bokep Indo Viral Update Guru Full","si":"https://thumbcdn.com/snaps/x11litobb987qhpp.jpg","sp":"https://thumbcdn.com/splash/x11litobb987qhpp.jpg","d":98,"vw":8004,"up":"2023-10-10 20:13:25","pe":"","pd":"https://myvidplay.com/d/0bime8ilvtgm","k":"Video Indo","src":"doodstream"},{"f":"5u6wvpapnhl3","t":"Viral Perkosa Seragam Sma Jilbab Tiktok Video Full Streaming","si":"https://thumbcdn.com/snaps/r2mvh4be38w8fioy.jpg","sp":"https://thumbcdn.com/splash/r2mvh4be38w8fioy.jpg","d":284,"vw":7184,"up":"2023-12-08 17:43:45","pe":"","pd":"https://myvidplay.com/d/5u6wvpapnhl3","k":"Video Jilbab","src":"doodstream"},{"f":"497hha3l6oyb","t":"Bokep Jepang Toket Gede Tanpa Sensor Bagus Com Indo SMA Guru Colmek","si":"https://thumbcdn.com/snaps/wr9p5zn7e5p68k2i.jpg","sp":"https://thumbcdn.com/splash/wr9p5zn7e5p68k2i.jpg","d":8787,"vw":7045,"up":"2024-05-31 02:33:21","pe":"","pd":"https://myvidplay.com/d/497hha3l6oyb","k":"Video Indo","src":"doodstream"},{"f":"1du1hc1lua48","t":"Jilbob Buat Pacar Dood Stream Full Tiktok Terbaru SMA Live","si":"https://thumbcdn.com/snaps/ch9uiianaaogvar9.jpg","sp":"https://thumbcdn.com/splash/ch9uiianaaogvar9.jpg","d":271,"vw":6916,"up":"2023-06-29 00:47:34","pe":"","pd":"https://myvidplay.com/d/1du1hc1lua48","k":"Video Viral","src":"doodstream"},{"f":"11pjjmwa497z","t":"Ukhty Tocil Lemes Bestie Di Entot Ayang Play Bokep Colmek Full Streaming","si":"https://thumbcdn.com/snaps/atv5il0uy4dpvv7z.jpg","sp":"https://thumbcdn.com/splash/atv5il0uy4dpvv7z.jpg","d":122,"vw":6760,"up":"2023-10-10 18:56:47","pe":"","pd":"https://myvidplay.com/d/11pjjmwa497z","k":"Video Viral","src":"doodstream"},{"f":"y8rplw9j46ex","t":"Bokep Indo Syakirah Viral Part Full Video Bebasindo Terbaru Tiktok Live SMA","si":"https://thumbcdn.com/snaps/e76cji06bt3kc097.jpg","sp":"https://thumbcdn.com/splash/e76cji06bt3kc097.jpg","d":166,"vw":6119,"up":"2023-12-15 18:56:50","pe":"","pd":"https://myvidplay.com/d/y8rplw9j46ex","k":"Video Indo","src":"doodstream"},{"f":"5ry9s208np2w","t":"Baby Feriosa Baju Transparan Mango Live Indonesia Jilbab Guru Full Video Terbaru","si":"https://thumbcdn.com/snaps/0r2mi8m4vbj6oqxm.jpg","sp":"https://thumbcdn.com/splash/0r2mi8m4vbj6oqxm.jpg","d":1004,"vw":5906,"up":"2023-11-27 02:26:18","pe":"","pd":"https://myvidplay.com/d/5ry9s208np2w","k":"Video Jilbab","src":"doodstream"},{"f":"1a011glvi83z","t":"Bokep Indo Janda Membuat Nyeri Twitter Guru Jilbab Full Tiktok","si":"https://thumbcdn.com/snaps/rkxax7k8g44aiwok.jpg","sp":"https://thumbcdn.com/splash/rkxax7k8g44aiwok.jpg","d":121,"vw":5753,"up":"2024-11-22 03:57:58","pe":"","pd":"https://myvidplay.com/d/1a011glvi83z","k":"Video Jilbab","src":"doodstream"},{"f":"zubs5luatc5y","t":"Bokep Indo Celva Seragam Sma Omek Barbar Lulustream Doodstream Live Tiktok Colmek","si":"https://thumbcdn.com/snaps/w49z3n8bqk7hmz29.jpg","sp":"https://thumbcdn.com/splash/w49z3n8bqk7hmz29.jpg","d":595,"vw":5701,"up":"2024-03-02 18:10:53","pe":"","pd":"https://myvidplay.com/d/zubs5luatc5y","k":"Video Indo","src":"doodstream"},{"f":"3rwsruqa59p6","t":"Lesby Cantik Mahasiswa Full Jilbab Doodstream Colmek","si":"https://thumbcdn.com/snaps/302gc08520vf4bsn.jpg","sp":"https://thumbcdn.com/splash/302gc08520vf4bsn.jpg","d":294,"vw":4226,"up":"2023-08-07 21:39:01","pe":"","pd":"https://myvidplay.com/d/3rwsruqa59p6","k":"Video Jilbab","src":"doodstream"},{"f":"9suqouzffoed","t":"Bokep Indo Tante Tobrut Di Gilir Sampe Squirt Bokepindoh Live Lulustream Doodstream","si":"https://thumbcdn.com/snaps/9mijn23nxfqz5w3x.jpg","sp":"https://thumbcdn.com/splash/9mijn23nxfqz5w3x.jpg","d":357,"vw":3859,"up":"2023-12-09 14:09:23","pe":"","pd":"https://myvidplay.com/d/9suqouzffoed","k":"Video Indo","src":"doodstream"},{"f":"upj5ysrr4ae1","t":"Lagi Belajar Dient D Kaka Skandal Indo Colmek Bokep Streaming","si":"https://thumbcdn.com/snaps/fmsyjx3lwt290uay.jpg","sp":"https://thumbcdn.com/splash/fmsyjx3lwt290uay.jpg","d":377,"vw":3612,"up":"2023-10-23 06:52:45","pe":"","pd":"https://myvidplay.com/d/upj5ysrr4ae1","k":"Video Skandal","src":"doodstream"},{"f":"0qnpmeixptj5","t":"Lesbian Amateur Fingering Their Pussy Mahasiswa Streaming Guru Doodstream Video","si":"https://thumbcdn.com/snaps/9746ern0gjynmy4j.jpg","sp":"https://thumbcdn.com/splash/9746ern0gjynmy4j.jpg","d":628,"vw":3161,"up":"2023-08-09 07:22:39","pe":"","pd":"https://myvidplay.com/d/0qnpmeixptj5","k":"Video Viral","src":"doodstream"},{"f":"43u9o5bso2ah","t":"Bokep Indo Langganan Psk Di Hotel Part Streaming Viral HD Terbaru Guru","si":"https://thumbcdn.com/snaps/t4x8jqysa1kve7fv.jpg","sp":"https://thumbcdn.com/splash/t4x8jqysa1kve7fv.jpg","d":289,"vw":3161,"up":"2023-08-08 00:21:22","pe":"","pd":"https://myvidplay.com/d/43u9o5bso2ah","k":"Video Indo","src":"doodstream"},{"f":"fozebz1b8jup","t":"Twitter Manlodek Ngentotin Stw Di Lantai Skandal Doodstream Tiktok Bokep Full","si":"https://thumbcdn.com/snaps/zqegtuiqyig4g2x4.jpg","sp":"https://thumbcdn.com/splash/zqegtuiqyig4g2x4.jpg","d":135,"vw":3096,"up":"2023-11-06 00:00:48","pe":"","pd":"https://myvidplay.com/d/fozebz1b8jup","k":"Video Skandal","src":"doodstream"},{"f":"0gfq6go3pts7","t":"Ngintip Kakak Mandi Pakai Hidden Cam Part Www Seksi One Dood Stream","si":"https://thumbcdn.com/snaps/ceo2lvelr8fc3g9s.jpg","sp":"https://thumbcdn.com/splash/ceo2lvelr8fc3g9s.jpg","d":532,"vw":3093,"up":"2023-10-02 19:56:43","pe":"","pd":"https://myvidplay.com/d/0gfq6go3pts7","k":"Video Viral","src":"doodstream"},{"f":"pv6i9ekhjib8","t":"Midnight Pool Ring Ai Sayama Seorang Guru Wanita Menikah Yang Diperkosa Di","si":"https://thumbcdn.com/snaps/05xy9ohhz9eq1yl4.jpg","sp":"https://thumbcdn.com/splash/05xy9ohhz9eq1yl4.jpg","d":7089,"vw":3068,"up":"2023-11-23 18:59:54","pe":"","pd":"https://myvidplay.com/d/pv6i9ekhjib8","k":"Video Viral","src":"doodstream"},{"f":"petm9bt9egrh","t":"Rekaman Seks Suami Istri Bocor Dan Tersebar Video Skandal Viral Doodstream Terbaru","si":"https://thumbcdn.com/snaps/um9crwljp0g2nnm1.jpg","sp":"https://thumbcdn.com/splash/um9crwljp0g2nnm1.jpg","d":641,"vw":2958,"up":"2023-10-19 21:57:05","pe":"","pd":"https://myvidplay.com/d/petm9bt9egrh","k":"Video Skandal","src":"doodstream"},{"f":"5i0rqeykwchr","t":"Dhela Mahasiswi Cantik Terbaru Full Viral Jilbab Lulustream","si":"https://thumbcdn.com/snaps/n9v9yz1b1tddak0j.jpg","sp":"https://thumbcdn.com/splash/n9v9yz1b1tddak0j.jpg","d":319,"vw":2848,"up":"2023-07-04 21:38:52","pe":"","pd":"https://myvidplay.com/d/5i0rqeykwchr","k":"Video Jilbab","src":"doodstream"},{"f":"wwx5zf6ydyym","t":"Beby Putie Jilat Titid Jilbab Terbaru Streaming Mahasiswa Full","si":"https://thumbcdn.com/snaps/uy2819l433yf9ypw.jpg","sp":"https://thumbcdn.com/splash/uy2819l433yf9ypw.jpg","d":9,"vw":2844,"up":"2023-09-01 20:45:05","pe":"","pd":"https://myvidplay.com/d/wwx5zf6ydyym","k":"Video Jilbab","src":"doodstream"},{"f":"cfsa6nvnbrgl","t":"Maaf Binimu Gua Pake Hri Ini HD Streaming Live Tiktok Doodstream","si":"https://thumbcdn.com/snaps/bv5aco98vgb09m0a.jpg","sp":"https://thumbcdn.com/splash/bv5aco98vgb09m0a.jpg","d":417,"vw":2793,"up":"2025-11-27 19:35:29","pe":"","pd":"https://myvidplay.com/d/cfsa6nvnbrgl","k":"Video Viral","src":"doodstream"},{"f":"ey414uc3027g","t":"Abg Cantik Padat Colmek Pakek Botol Parfum Di Lantai Doodstream Video Terbaru","si":"https://thumbcdn.com/snaps/09j39f1b70omemt7.jpg","sp":"https://thumbcdn.com/splash/09j39f1b70omemt7.jpg","d":91,"vw":2747,"up":"2024-02-16 07:35:10","pe":"","pd":"https://myvidplay.com/d/ey414uc3027g","k":"Video Viral","src":"doodstream"},{"f":"suc9d17siaow","t":"Yang Viral Entot Adik Ipar Sange Sampai Crot Puas Live Bokep SMA","si":"https://thumbcdn.com/snaps/cd8ic7zkui0o66p9.jpg","sp":"https://thumbcdn.com/splash/cd8ic7zkui0o66p9.jpg","d":65,"vw":2684,"up":"2024-03-01 04:48:53","pe":"","pd":"https://myvidplay.com/d/suc9d17siaow","k":"Video Viral","src":"doodstream"},{"f":"q4sbo8tl45ft","t":"Bocil Tele Andini Bjj Guru Streaming Video Bokep Tiktok","si":"https://thumbcdn.com/snaps/em5rmpzeemacbmze.jpg","sp":"https://thumbcdn.com/splash/em5rmpzeemacbmze.jpg","d":11,"vw":2653,"up":"2024-02-02 07:28:52","pe":"","pd":"https://myvidplay.com/d/q4sbo8tl45ft","k":"Video Viral","src":"doodstream"},{"f":"l7yn2wew4j5l","t":"Bokep Indo Istri Tetangga Terlalu Menggoda Di Jalan Guru Live Terbaru Colmek","si":"","sp":"","d":348,"vw":2419,"up":"2025-10-08 07:41:34","pe":"","pd":"","k":"Video Indo","src":"lulustream"},{"f":"w2c6w0nywyy8","t":"Bokep Abg Live Mesum Dedek Comel Bugil Id Lulustream Viral Skandal Video","si":"https://thumbcdn.com/snaps/mylqcxvdrw5og9kt.jpg","sp":"https://thumbcdn.com/splash/mylqcxvdrw5og9kt.jpg","d":2650,"vw":2405,"up":"2024-03-27 20:02:50","pe":"","pd":"https://myvidplay.com/d/w2c6w0nywyy8","k":"Video Skandal","src":"doodstream"},{"f":"02mg3m0wrjl6","t":"Bokep Indo Cecewi Bugil Gesek Meki Ke Bantal Doodstream Full Skandal Colmek","si":"https://thumbcdn.com/snaps/y9kugdafhrzspfdx.jpg","sp":"https://thumbcdn.com/splash/y9kugdafhrzspfdx.jpg","d":639,"vw":2358,"up":"2024-02-16 13:47:59","pe":"","pd":"https://myvidplay.com/d/02mg3m0wrjl6","k":"Video Skandal","src":"doodstream"},{"f":"67ppgpxgi9np","t":"J Nella Dood Stream Terbaru Update HD Indo","si":"https://thumbcdn.com/snaps/3v101j85jrr1gx66.jpg","sp":"https://thumbcdn.com/splash/3v101j85jrr1gx66.jpg","d":273,"vw":2174,"up":"2023-06-30 11:59:14","pe":"","pd":"https://myvidplay.com/d/67ppgpxgi9np","k":"Video Indo","src":"doodstream"},{"f":"8bqcgasjimxh","t":"Bokep Pacar Baru Pulang Kerja Kehujanan Langsung Entot Twitter Doodstream Live Jilbab","si":"https://thumbcdn.com/snaps/6wrriayh3zexjwzp.jpg","sp":"https://thumbcdn.com/splash/6wrriayh3zexjwzp.jpg","d":752,"vw":2167,"up":"2023-08-16 15:22:29","pe":"","pd":"https://myvidplay.com/d/8bqcgasjimxh","k":"Video Jilbab","src":"doodstream"},{"f":"4y2leuhqvagn","t":"Chinese Big Tits Brunette Girl Li Nana With Enjoy Fucking A Hard","si":"https://thumbcdn.com/snaps/7ab45ptj0jp4vvab.jpg","sp":"https://thumbcdn.com/splash/7ab45ptj0jp4vvab.jpg","d":785,"vw":2111,"up":"2024-06-05 12:46:08","pe":"","pd":"https://myvidplay.com/d/4y2leuhqvagn","k":"Video Viral","src":"doodstream"},{"f":"jnwz21a22kkx","t":"Sebelum Bobo Pap Memek Untuk Pacar Video Mahasiswa Jilbab Twitter Skandal","si":"https://thumbcdn.com/snaps/ez2gyx35bt00p9qp.jpg","sp":"https://thumbcdn.com/splash/ez2gyx35bt00p9qp.jpg","d":98,"vw":1976,"up":"2023-10-20 02:45:07","pe":"","pd":"https://myvidplay.com/d/jnwz21a22kkx","k":"Video Jilbab","src":"doodstream"},{"f":"w7bvrbrhzxx5","t":"Bigo Hot Goyang Ebot Belahant Mbem Enak Indo Skandal Mahasiswa Colmek Jilbab","si":"https://thumbcdn.com/snaps/p0afsztty0sgilkp.jpg","sp":"https://thumbcdn.com/splash/p0afsztty0sgilkp.jpg","d":185,"vw":1890,"up":"2024-03-08 18:39:52","pe":"","pd":"https://myvidplay.com/d/w7bvrbrhzxx5","k":"Video Jilbab","src":"doodstream"},{"f":"kdwysu3z6kfz","t":"Bokep Indo Viral Aci Abg Toge Mainin Meki SMA HD Full Guru","si":"https://thumbcdn.com/snaps/yauj10ffmw8jb6vg.jpg","sp":"https://thumbcdn.com/splash/yauj10ffmw8jb6vg.jpg","d":183,"vw":1826,"up":"2023-11-12 13:15:18","pe":"","pd":"https://myvidplay.com/d/kdwysu3z6kfz","k":"Video Indo","src":"doodstream"},{"f":"dn9zeai6esf8","t":"Fika Esempeh Dood Stream Poop Hd Streaming Full Terbaru Lulustream Guru","si":"https://thumbcdn.com/snaps/ahc78vho1kmgmj00.jpg","sp":"https://thumbcdn.com/splash/ahc78vho1kmgmj00.jpg","d":129,"vw":1813,"up":"2024-02-07 17:08:30","pe":"","pd":"https://myvidplay.com/d/dn9zeai6esf8","k":"Video Viral","src":"doodstream"},{"f":"g5h0wvhhr21z","t":"Karya Lokal Homemade Binal Sange Ceweknya Doodstream Indo Jilbab Update Guru","si":"https://thumbcdn.com/snaps/kki00g8amlyakftn.jpg","sp":"https://thumbcdn.com/splash/kki00g8amlyakftn.jpg","d":765,"vw":1767,"up":"2023-10-24 11:23:48","pe":"","pd":"https://myvidplay.com/d/g5h0wvhhr21z","k":"Video Jilbab","src":"doodstream"},{"f":"4gq7dswpfq8r","t":"Bokep Indo Abg Imut Ngewe Depan Cermin Bokebind Mp At Streamtape Com","si":"https://thumbcdn.com/snaps/b6ouqf26ay6pbplz.jpg","sp":"https://thumbcdn.com/splash/b6ouqf26ay6pbplz.jpg","d":86,"vw":1746,"up":"2023-10-29 17:19:13","pe":"","pd":"https://myvidplay.com/d/4gq7dswpfq8r","k":"Video Indo","src":"doodstream"},{"f":"hooid06n6u4o","t":"Bby Moy Live Sange Skandal Colmek HD Update","si":"https://thumbcdn.com/snaps/t8epxksh01b31vq6.jpg","sp":"https://thumbcdn.com/splash/t8epxksh01b31vq6.jpg","d":698,"vw":1588,"up":"2023-08-09 10:50:40","pe":"","pd":"https://myvidplay.com/d/hooid06n6u4o","k":"Video Skandal","src":"doodstream"},{"f":"rlhwmurhkh7s","t":"Prank Pacar Di Dapur Bugilin Kobel Memeknya Ngentot Yuk Duniastreaming Dot Fun","si":"https://thumbcdn.com/snaps/eoy7k1kmjwuylyo3.jpg","sp":"https://thumbcdn.com/splash/eoy7k1kmjwuylyo3.jpg","d":803,"vw":1519,"up":"2024-03-08 11:57:49","pe":"","pd":"https://myvidplay.com/d/rlhwmurhkh7s","k":"Video Viral","src":"doodstream"},{"f":"mgzyr1figzrk","t":"Alondra Uting Coklat Tete Jumbo Twitter Streaming Indo Terbaru SMA","si":"https://thumbcdn.com/snaps/r0agxnvmuae1h829.jpg","sp":"https://thumbcdn.com/splash/r0agxnvmuae1h829.jpg","d":3194,"vw":1486,"up":"2023-09-22 20:30:50","pe":"","pd":"https://myvidplay.com/d/mgzyr1figzrk","k":"Video Indo","src":"doodstream"},{"f":"2feen6y9bdcj","t":"Zara Pakai Lingerie Hitam Streaming Tiktok Colmek Skandal Indo","si":"https://thumbcdn.com/snaps/iblnlkcxie5wc44g.jpg","sp":"https://thumbcdn.com/splash/iblnlkcxie5wc44g.jpg","d":1174,"vw":1478,"up":"2025-01-13 05:24:18","pe":"","pd":"https://myvidplay.com/d/2feen6y9bdcj","k":"Video Skandal","src":"doodstream"},{"f":"2mobvry5u2jw","t":"Sma Pulang Dari Sekolah Langsung Gas Full HD Tiktok Colmek Twitter","si":"https://thumbcdn.com/snaps/g14479dyymsfui06.jpg","sp":"https://thumbcdn.com/splash/g14479dyymsfui06.jpg","d":155,"vw":1471,"up":"2023-12-17 11:51:59","pe":"","pd":"https://myvidplay.com/d/2mobvry5u2jw","k":"Video Viral","src":"doodstream"},{"f":"jn4kumsv18w1","t":"Bokep Indo Ukhti Baby Ica Sedang Pengen Terbaru Jilbab Lulustream Video","si":"https://thumbcdn.com/snaps/3a9144zh0novzzn1.jpg","sp":"https://thumbcdn.com/splash/3a9144zh0novzzn1.jpg","d":873,"vw":1445,"up":"2024-03-12 03:25:32","pe":"","pd":"https://myvidplay.com/d/jn4kumsv18w1","k":"Video Jilbab","src":"doodstream"},{"f":"9degv9j3s8hl","t":"Paksa Masuk Ke Memek Yang Masih Perawan Full Tiktok Mahasiswa Lulustream Terbaru","si":"https://thumbcdn.com/snaps/69qsm22wghew9kji.jpg","sp":"https://thumbcdn.com/splash/69qsm22wghew9kji.jpg","d":263,"vw":1427,"up":"2024-03-06 23:58:33","pe":"","pd":"https://myvidplay.com/d/9degv9j3s8hl","k":"Video Viral","src":"doodstream"},{"f":"znyioj9xa0u9","t":"Paklik Sewa Lonte Part Poop Hd Viral Update Full Skandal Lulustream","si":"https://thumbcdn.com/snaps/2cvx25r80upy516c.jpg","sp":"https://thumbcdn.com/splash/2cvx25r80upy516c.jpg","d":3049,"vw":1388,"up":"2023-11-09 19:13:51","pe":"","pd":"https://myvidplay.com/d/znyioj9xa0u9","k":"Video Skandal","src":"doodstream"},{"f":"p3jr9ls2bbbl","t":"Goyangan Pantat Semok Dood Stream Mahasiswa Live Update Lulustream Bokep","si":"https://thumbcdn.com/snaps/0r9twwkbi940q0ks.jpg","sp":"https://thumbcdn.com/splash/0r9twwkbi940q0ks.jpg","d":339,"vw":1307,"up":"2023-10-31 01:47:14","pe":"","pd":"https://myvidplay.com/d/p3jr9ls2bbbl","k":"Video Viral","src":"doodstream"},{"f":"db24vmr0evsb","t":"Lebih Baik Ku Pasrah Daripada Ayang Marah Indoxpanas Twitter Video SMA Update","si":"https://thumbcdn.com/snaps/687n6ef0d4osq76v.jpg","sp":"https://thumbcdn.com/splash/687n6ef0d4osq76v.jpg","d":45,"vw":1242,"up":"2023-11-08 19:46:40","pe":"","pd":"https://myvidplay.com/d/db24vmr0evsb","k":"Video Indo","src":"doodstream"},{"f":"xvrtc5u1al5i","t":"Pemeriksaan Lubang Anus Dan Memek Part Viral Colmek Twitter Update Live","si":"https://thumbcdn.com/snaps/19kcanmadw82ev0c.jpg","sp":"https://thumbcdn.com/splash/19kcanmadw82ev0c.jpg","d":3933,"vw":1137,"up":"2023-12-06 18:37:19","pe":"","pd":"https://myvidplay.com/d/xvrtc5u1al5i","k":"Video Viral","src":"doodstream"},{"f":"193tq2r2os9k","t":"Missbrewc Horny Pokeh Croot Streaming Doodstream HD Lulustream SMA","si":"https://thumbcdn.com/snaps/b42i8umjm8amymio.jpg","sp":"https://thumbcdn.com/splash/b42i8umjm8amymio.jpg","d":323,"vw":1135,"up":"2023-10-18 17:15:50","pe":"","pd":"https://myvidplay.com/d/193tq2r2os9k","k":"Video Viral","src":"doodstream"},{"f":"ozj24mogpp9y","t":"Bokep Jilbab Sma Pap Di Kelas Twitter Doodstream HD Viral Indo","si":"https://thumbcdn.com/snaps/rahy1s6vs221839j.jpg","sp":"https://thumbcdn.com/splash/rahy1s6vs221839j.jpg","d":40,"vw":1053,"up":"2024-09-14 17:40:41","pe":"","pd":"https://myvidplay.com/d/ozj24mogpp9y","k":"Video Jilbab","src":"doodstream"},{"f":"dkahc7nyg7yw","t":"Bokep Jilbab Viral Mesum Dalam Mobil Xbokep Fb HD Skandal Live Colmek","si":"https://thumbcdn.com/snaps/eec2djd4ulvmzkqp.jpg","sp":"https://thumbcdn.com/splash/eec2djd4ulvmzkqp.jpg","d":788,"vw":1047,"up":"2023-11-30 13:37:05","pe":"","pd":"https://myvidplay.com/d/dkahc7nyg7yw","k":"Video Jilbab","src":"doodstream"},{"f":"p814b1ildzia","t":"Nonton Ini Berasa Kaya Ngintip Guru Jilbab Bokep Lulustream Video","si":"https://thumbcdn.com/snaps/qg9jb1gbrka95dkt.jpg","sp":"https://thumbcdn.com/splash/qg9jb1gbrka95dkt.jpg","d":628,"vw":1005,"up":"2023-11-30 13:35:39","pe":"","pd":"https://myvidplay.com/d/p814b1ildzia","k":"Video Jilbab","src":"doodstream"},{"f":"4b4ag6cxxipw","t":"Kumpulan Video Aulia Salsa Ukhty Tiktok Viral Update Mahasiswa HD Twitter Live","si":"https://thumbcdn.com/snaps/pwqck1rr53zjqsvd.jpg","sp":"https://thumbcdn.com/splash/pwqck1rr53zjqsvd.jpg","d":1173,"vw":984,"up":"2025-01-13 05:27:14","pe":"","pd":"https://myvidplay.com/d/4b4ag6cxxipw","k":"Video Viral","src":"doodstream"},{"f":"ailsxczz69cs","t":"Live Show Bugil Host Semok Riri Ratih Com Dood Stream","si":"https://thumbcdn.com/snaps/0p0e4bclfm3cago4.jpg","sp":"https://thumbcdn.com/splash/0p0e4bclfm3cago4.jpg","d":556,"vw":970,"up":"2023-10-10 20:52:57","pe":"","pd":"https://myvidplay.com/d/ailsxczz69cs","k":"Video Viral","src":"doodstream"},{"f":"yw56dp7ty6vo","t":"Bokep Indo Maela Kostum Suster Hot Maelaekitty Indojav Guru Viral HD Colmek","si":"https://thumbcdn.com/snaps/8rw92dh6qptzn8ot.jpg","sp":"https://thumbcdn.com/splash/8rw92dh6qptzn8ot.jpg","d":1351,"vw":957,"up":"2023-08-17 18:48:47","pe":"","pd":"https://myvidplay.com/d/yw56dp7ty6vo","k":"Video Indo","src":"doodstream"},{"f":"lfsu6114optg","t":"Live Show Ngewe Sampe Klimaks Miss Ai Chan Viral Streaming Update Indo","si":"https://thumbcdn.com/snaps/k9ih01lez8gfzhdb.jpg","sp":"https://thumbcdn.com/splash/k9ih01lez8gfzhdb.jpg","d":2426,"vw":954,"up":"2023-10-22 22:15:13","pe":"","pd":"https://myvidplay.com/d/lfsu6114optg","k":"Video Indo","src":"doodstream"},{"f":"mhxnm37qat91","t":"Igo Pt Tele Bokepindmantap SMA Mahasiswa Live Guru Terbaru","si":"https://thumbcdn.com/snaps/idn7zpqr7gaytffg.jpg","sp":"https://thumbcdn.com/splash/idn7zpqr7gaytffg.jpg","d":76,"vw":862,"up":"2025-12-11 16:22:27","pe":"","pd":"https://myvidplay.com/d/mhxnm37qat91","k":"Video Viral","src":"doodstream"},{"f":"j8lcmrdurnyv","t":"Pulang Kerja Langsung Layani Suami Full Update Terbaru Video Twitter","si":"https://thumbcdn.com/snaps/byeqwcx5p7gx44gl.jpg","sp":"https://thumbcdn.com/splash/byeqwcx5p7gx44gl.jpg","d":542,"vw":819,"up":"2024-01-05 10:38:07","pe":"","pd":"https://myvidplay.com/d/j8lcmrdurnyv","k":"Video Viral","src":"doodstream"},{"f":"1dw0vibxswfh","t":"Maria Sensei Enak Di Mobil Kimcilonly Terbaru Video Twitter Jilbab SMA","si":"https://thumbcdn.com/snaps/faw1g906hr2kor7a.jpg","sp":"https://thumbcdn.com/splash/faw1g906hr2kor7a.jpg","d":2558,"vw":785,"up":"2023-10-16 03:16:45","pe":"","pd":"https://myvidplay.com/d/1dw0vibxswfh","k":"Video Jilbab","src":"doodstream"},{"f":"cq7aceoedsyo","t":"Vidio Bokep Avtub Abg Suka Lesbian Xbokep Fb Colmek Terbaru Indo Update","si":"https://thumbcdn.com/snaps/8ify4g2y5ukk708p.jpg","sp":"https://thumbcdn.com/splash/8ify4g2y5ukk708p.jpg","d":450,"vw":754,"up":"2023-11-28 21:13:59","pe":"","pd":"https://myvidplay.com/d/cq7aceoedsyo","k":"Video Indo","src":"doodstream"},{"f":"1k848k3ykhwe","t":"Video Viral Tiktok Tumpah Dalem Doodstream Mahasiswa SMA Indo Guru","si":"https://thumbcdn.com/snaps/l6gdvzq9p0w8j973.jpg","sp":"https://thumbcdn.com/splash/l6gdvzq9p0w8j973.jpg","d":61,"vw":728,"up":"2024-03-09 04:53:07","pe":"","pd":"https://myvidplay.com/d/1k848k3ykhwe","k":"Video Indo","src":"doodstream"},{"f":"igtyqgllplg6","t":"Maen Ke Kost Janda Cantik SMA Terbaru Guru Live Full","si":"https://thumbcdn.com/snaps/d3x7wmno5ni6setu.jpg","sp":"https://thumbcdn.com/splash/d3x7wmno5ni6setu.jpg","d":49,"vw":708,"up":"2023-12-05 00:59:39","pe":"","pd":"https://myvidplay.com/d/igtyqgllplg6","k":"Video Viral","src":"doodstream"},{"f":"re8kfe65plqu","t":"Kisah Abg Suka Selingkuh Dengan Bos Besar Kirara Asuka Dood Stream","si":"https://thumbcdn.com/snaps/fluezttyimptp8wn.jpg","sp":"https://thumbcdn.com/splash/fluezttyimptp8wn.jpg","d":7120,"vw":605,"up":"2023-11-09 19:15:15","pe":"","pd":"https://myvidplay.com/d/re8kfe65plqu","k":"Video Viral","src":"doodstream"},{"f":"zibt5ma2nu30","t":"Bokep Cina Indo Ngewe Puas Banget Viral Terbaru Lulustream Skandal Tiktok","si":"https://thumbcdn.com/snaps/pcynmvxi7dbtpqrn.jpg","sp":"https://thumbcdn.com/splash/pcynmvxi7dbtpqrn.jpg","d":1440,"vw":559,"up":"2024-08-08 02:06:52","pe":"","pd":"https://myvidplay.com/d/zibt5ma2nu30","k":"Video Skandal","src":"doodstream"},{"f":"92usz4666pts","t":"Bokep Terbaru Abg Cantik Colmek Desah Onlyfans Mahasiswa Twitter Viral SMA Streaming","si":"https://thumbcdn.com/snaps/z7vnhyrr9upqdbt2.jpg","sp":"https://thumbcdn.com/splash/z7vnhyrr9upqdbt2.jpg","d":250,"vw":507,"up":"2025-01-12 13:42:00","pe":"","pd":"https://myvidplay.com/d/92usz4666pts","k":"Video Viral","src":"doodstream"},{"f":"lzxpwu221n2y","t":"Video Yandex Pelatihan Langsung Terkesima Melihat Badan Tante Mahasiswa Full Terbaru Guru","si":"https://thumbcdn.com/snaps/bo1w5i0fzgphtgim.jpg","sp":"https://thumbcdn.com/splash/bo1w5i0fzgphtgim.jpg","d":494,"vw":459,"up":"2024-04-04 02:50:22","pe":"","pd":"https://myvidplay.com/d/lzxpwu221n2y","k":"Video Viral","src":"doodstream"},{"f":"62tf5xrotosg","t":"Miss Alondra Putih Mulus Sekseh Live SMA Terbaru Tiktok Viral","si":"https://thumbcdn.com/snaps/dcd8wsb5cr1zdptk.jpg","sp":"https://thumbcdn.com/splash/dcd8wsb5cr1zdptk.jpg","d":1697,"vw":459,"up":"2023-12-11 11:16:40","pe":"","pd":"https://myvidplay.com/d/62tf5xrotosg","k":"Video Viral","src":"doodstream"},{"f":"nfezsmnl551e","t":"Aiiyrina Tiktoker Guru Update Viral Doodstream Streaming","si":"https://thumbcdn.com/snaps/wl8zfmnyelvcia54.jpg","sp":"https://thumbcdn.com/splash/wl8zfmnyelvcia54.jpg","d":2,"vw":454,"up":"2023-09-01 20:54:07","pe":"","pd":"https://myvidplay.com/d/nfezsmnl551e","k":"Video Viral","src":"doodstream"},{"f":"7hadn0b79x9u","t":"Bokep Indo Valerina Gemoy Bling Bugil Dance Erotis Terbaru Viral HD Streaming","si":"https://thumbcdn.com/snaps/5sgayvveeczefryz.jpg","sp":"https://thumbcdn.com/splash/5sgayvveeczefryz.jpg","d":3600,"vw":449,"up":"2024-03-09 04:57:28","pe":"","pd":"https://myvidplay.com/d/7hadn0b79x9u","k":"Video Indo","src":"doodstream"},{"f":"4eztk1neycee","t":"New Hijab Viral Montok Ml Di Sofa Simantan Bokep Terbaru Guru Tiktok","si":"https://thumbcdn.com/snaps/u2u1dei1xfacmqdj.jpg","sp":"https://thumbcdn.com/splash/u2u1dei1xfacmqdj.jpg","d":557,"vw":435,"up":"2025-01-13 05:24:47","pe":"","pd":"https://myvidplay.com/d/4eztk1neycee","k":"Video Viral","src":"doodstream"},{"f":"rf4tmxt25kz0","t":"Lu Fokus Nge Rekam Aja Bro Ga Perlu Ikut Colmek Viral Twitter","si":"https://thumbcdn.com/snaps/4l34kg3gyf0octpw.jpg","sp":"https://thumbcdn.com/splash/4l34kg3gyf0octpw.jpg","d":140,"vw":423,"up":"2025-01-20 05:02:39","pe":"","pd":"https://myvidplay.com/d/rf4tmxt25kz0","k":"Video Viral","src":"doodstream"},{"f":"oizchkf62j7c","t":"Bokep Jamilah Tobrut Ngewe Layani Orang Lulustream Tiktok Twitter Terbaru Viral","si":"https://thumbcdn.com/snaps/cty1z7fx67808dqz.jpg","sp":"https://thumbcdn.com/splash/cty1z7fx67808dqz.jpg","d":1861,"vw":392,"up":"2024-08-31 14:43:25","pe":"","pd":"https://myvidplay.com/d/oizchkf62j7c","k":"Video Viral","src":"doodstream"},{"f":"v1jqpg9d238f","t":"Lagi Enak Tidur Di Kulum Tiktok Video Indo Skandal Guru","si":"","sp":"","d":373,"vw":383,"up":"2025-09-20 18:06:04","pe":"","pd":"","k":"Video Skandal","src":"lulustream"},{"f":"czxqrwnj3h9c","t":"Hijab Nakal Main Dengan Pacar Tercinta Video Bokep Twitter SMA Viral","si":"https://thumbcdn.com/snaps/d44hfe1sjv6q31sr.jpg","sp":"https://thumbcdn.com/splash/d44hfe1sjv6q31sr.jpg","d":560,"vw":345,"up":"2025-12-11 16:22:27","pe":"","pd":"https://myvidplay.com/d/czxqrwnj3h9c","k":"Video Viral","src":"doodstream"},{"f":"ix6c8favwu9m","t":"Amel HD Lulustream Jilbab Full Terbaru","si":"https://thumbcdn.com/snaps/jfow4c3dc7md2r4k.jpg","sp":"https://thumbcdn.com/splash/jfow4c3dc7md2r4k.jpg","d":3265,"vw":287,"up":"2025-02-01 21:28:49","pe":"","pd":"https://myvidplay.com/d/ix6c8favwu9m","k":"Video Jilbab","src":"doodstream"},{"f":"bbz5g7eujzlu","t":"Seru Tube Sleep Call Sama Yeni Tocil Abg Yo Host Mango Id","si":"https://thumbcdn.com/snaps/ecmglvqnlpe6bpjq.jpg","sp":"https://thumbcdn.com/splash/ecmglvqnlpe6bpjq.jpg","d":1361,"vw":254,"up":"2024-02-04 07:59:17","pe":"","pd":"https://myvidplay.com/d/bbz5g7eujzlu","k":"Video Viral","src":"doodstream"},{"f":"p4rbvnkkcodl","t":"Novi Siswi Sma Tocil Doyan Kontol Twitter Guru Video Mahasiswa Doodstream","si":"https://thumbcdn.com/snaps/6bie078fzz09wd2r.jpg","sp":"https://thumbcdn.com/splash/6bie078fzz09wd2r.jpg","d":182,"vw":220,"up":"2025-01-13 05:24:39","pe":"","pd":"https://myvidplay.com/d/p4rbvnkkcodl","k":"Video Viral","src":"doodstream"},{"f":"dfxv9674aol4","t":"Angelchan Twitter Ukhtinakall Viral HD Terbaru Mahasiswa Update","si":"https://thumbcdn.com/snaps/ijohv9ev5kj5aza6.jpg","sp":"https://thumbcdn.com/splash/ijohv9ev5kj5aza6.jpg","d":70,"vw":210,"up":"2025-01-13 05:27:20","pe":"","pd":"https://myvidplay.com/d/dfxv9674aol4","k":"Video Viral","src":"doodstream"},{"f":"n1r1j0htq8ib","t":"Kontol Pacar Di Jepit Tete Tiktok Indo Video Terbaru Streaming","si":"https://thumbcdn.com/snaps/rin7orjtsrtciqwf.jpg","sp":"https://thumbcdn.com/splash/rin7orjtsrtciqwf.jpg","d":94,"vw":191,"up":"2024-05-08 16:03:33","pe":"","pd":"https://myvidplay.com/d/n1r1j0htq8ib","k":"Video Indo","src":"doodstream"},{"f":"5zide551kbjc","t":"Bokep Viral Live Colmek Group Kelas Telegram Sangetube Terbaru Skandal Doodstream Jilbab","si":"https://thumbcdn.com/snaps/mhbmeiut78nt7jwp.jpg","sp":"https://thumbcdn.com/splash/mhbmeiut78nt7jwp.jpg","d":546,"vw":187,"up":"2023-11-28 08:46:38","pe":"","pd":"https://myvidplay.com/d/5zide551kbjc","k":"Video Jilbab","src":"doodstream"},{"f":"n6pr729pb852","t":"Janda Rajinbbc Doodstream Mahasiswa Tiktok Colmek Video","si":"","sp":"","d":118,"vw":180,"up":"2025-11-17 13:28:28","pe":"","pd":"","k":"Video Viral","src":"lulustream"},{"f":"tzm7pvufjh66","t":"Bokep Indo Cewek Bandung Mulus Lagi Sange Streaming Guru Mahasiswa Lulustream","si":"https://thumbcdn.com/snaps/xis8cgxwzif4lt14.jpg","sp":"https://thumbcdn.com/splash/xis8cgxwzif4lt14.jpg","d":180,"vw":175,"up":"2024-02-08 12:02:43","pe":"","pd":"https://myvidplay.com/d/tzm7pvufjh66","k":"Video Indo","src":"doodstream"},{"f":"cgq779948cpd","t":"Spg Perhotelan Teriak Ampun Dikentot Dood Stream Lulustream Doodstream Update Jilbab Streaming","si":"https://thumbcdn.com/snaps/0cz53xjysslq76d2.jpg","sp":"https://thumbcdn.com/splash/0cz53xjysslq76d2.jpg","d":114,"vw":142,"up":"2025-10-16 15:37:17","pe":"","pd":"https://myvidplay.com/d/cgq779948cpd","k":"Video Jilbab","src":"doodstream"},{"f":"00me67rgzjhn","t":"Septiani Tiktok Viral SMA Skandal Streaming Terbaru Update","si":"","sp":"","d":65,"vw":139,"up":"2025-07-04 01:07:33","pe":"","pd":"","k":"Video Skandal","src":"lulustream"},{"f":"fxg08z0mxq76","t":"Masih Sma Udah Jago Doggy Twitter Update Doodstream Colmek HD","si":"https://thumbcdn.com/snaps/uf39mkoxsrfmw0xq.jpg","sp":"https://thumbcdn.com/splash/uf39mkoxsrfmw0xq.jpg","d":226,"vw":132,"up":"2025-01-13 05:23:43","pe":"","pd":"https://myvidplay.com/d/fxg08z0mxq76","k":"Video Viral","src":"doodstream"},{"f":"bv3htmls3rx8","t":"Miss Bi Ukhti Mulai Berani Pamer Belahan Play Bokep Dood Stream","si":"https://thumbcdn.com/snaps/eziah8usuur9k2bl.jpg","sp":"https://thumbcdn.com/splash/eziah8usuur9k2bl.jpg","d":261,"vw":114,"up":"2025-01-18 06:04:09","pe":"","pd":"https://myvidplay.com/d/bv3htmls3rx8","k":"Video Viral","src":"doodstream"},{"f":"6yd0tj6qrs1i","t":"Cewek Tocil Colmek Sheren SMA Mahasiswa Viral Video Jilbab","si":"https://thumbcdn.com/snaps/l7vzk35xjwxbpyxe.jpg","sp":"https://thumbcdn.com/splash/l7vzk35xjwxbpyxe.jpg","d":485,"vw":113,"up":"2025-01-16 06:45:32","pe":"","pd":"https://myvidplay.com/d/6yd0tj6qrs1i","k":"Video Jilbab","src":"doodstream"},{"f":"5dedist2fcy6","t":"Nemenin Pake Baju Hijabers Bening Mulus Video Terbaru SMA Twitter Viral","si":"https://thumbcdn.com/snaps/kv58wh6b8x0bs0rb.jpg","sp":"https://thumbcdn.com/splash/kv58wh6b8x0bs0rb.jpg","d":600,"vw":108,"up":"2024-12-19 21:38:57","pe":"","pd":"https://myvidplay.com/d/5dedist2fcy6","k":"Video Viral","src":"doodstream"},{"f":"6jeg96dk0d8i","t":"Perdana Live Dan Ngewe Full Update Streaming Tiktok Terbaru","si":"https://thumbcdn.com/snaps/l15qh729dj1iwwdk.jpg","sp":"https://thumbcdn.com/splash/l15qh729dj1iwwdk.jpg","d":316,"vw":84,"up":"2025-01-13 05:19:59","pe":"","pd":"https://myvidplay.com/d/6jeg96dk0d8i","k":"Video Viral","src":"doodstream"},{"f":"tit69bf5mlp8","t":"Maba Akbid Lulustream Video Terbaru Bokep Skandal","si":"https://thumbcdn.com/snaps/dk559371uvfolqfa.jpg","sp":"https://thumbcdn.com/splash/dk559371uvfolqfa.jpg","d":140,"vw":59,"up":"2025-10-17 18:04:54","pe":"","pd":"https://myvidplay.com/d/tit69bf5mlp8","k":"Video Skandal","src":"doodstream"},{"f":"02e5u4pxkrff","t":"Bokep Kost Ayang Sange Pengen Di Puasin Id Mahasiswa Terbaru Jilbab Lulustream","si":"https://thumbcdn.com/snaps/9d90pull44z7mnus.jpg","sp":"https://thumbcdn.com/splash/9d90pull44z7mnus.jpg","d":222,"vw":57,"up":"2025-12-02 03:44:52","pe":"","pd":"https://myvidplay.com/d/02e5u4pxkrff","k":"Video Jilbab","src":"doodstream"},{"f":"9so2g4fvlhos","t":"Lv Jilbab Video Lulustream Twitter Mahasiswa","si":"https://thumbcdn.com/snaps/chqpbgto7my77az5.jpg","sp":"https://thumbcdn.com/splash/chqpbgto7my77az5.jpg","d":316,"vw":48,"up":"2025-01-18 05:47:21","pe":"","pd":"https://myvidplay.com/d/9so2g4fvlhos","k":"Video Jilbab","src":"doodstream"},{"f":"ah2lhf0esbjx","t":"Thia Azman Skandal Viral HD Doodstream Twitter","si":"https://thumbcdn.com/snaps/unf5xrmg04b56ugf.jpg","sp":"https://thumbcdn.com/splash/unf5xrmg04b56ugf.jpg","d":74,"vw":44,"up":"2025-01-13 05:26:00","pe":"","pd":"https://myvidplay.com/d/ah2lhf0esbjx","k":"Video Skandal","src":"doodstream"},{"f":"c1pqy1wmpn21","t":"Ngasih Jatah Buat Pacar Biar Langgeng SMA Indo Viral Twitter Doodstream","si":"https://thumbcdn.com/snaps/3twd3vi92d5pqwre.jpg","sp":"https://thumbcdn.com/splash/3twd3vi92d5pqwre.jpg","d":152,"vw":21,"up":"2025-10-16 15:36:15","pe":"","pd":"https://myvidplay.com/d/c1pqy1wmpn21","k":"Video Indo","src":"doodstream"}]