[{"f":"42snhv9lvp1z","t":"Zz Viral Sma Colmek Hot Dood Stream Lulustream Telegram Memeksiana Terupdate Folder","t_esc":"Zz Viral Sma Colmek Hot Dood Stream Lulustream Telegram Memeksiana Terupdate Folder","ln":"00:02:12","sp":"https://wsrv.nl/?url=https%3A//thumbcdn.com/splash/fr2ylx94iqwptseq.jpg","si":"https://wsrv.nl/?url=https%3A//thumbcdn.com/snaps/fr2ylx94iqwptseq.jpg","vw":"2510","vw_fmt":"2.5K","up":"2023-12-01 10:46:39","up_fmt":"1 Des 2023","up_short":"1 Des","pg":68},{"f":"2j3hulbq7ll6","t":"Zz Maura Ngajarin Bocah Smp Ngetott Simontok Asupan Doodflix Live Bokep","t_esc":"Zz Maura Ngajarin Bocah Smp Ngetott Simontok Asupan Doodflix Live Bokep","ln":"00:06:06","sp":"https://wsrv.nl/?url=https%3A//thumbcdn.com/splash/buwr715xrur7qqcz.jpg","si":"https://wsrv.nl/?url=https%3A//thumbcdn.com/snaps/buwr715xrur7qqcz.jpg","vw":"46917","vw_fmt":"46.9K","up":"2023-10-26 08:59:59","up_fmt":"26 Okt 2023","up_short":"26 Okt","pg":80},{"f":"1s74t61ni7l9","t":"Zz Bokep Indo Hijab Cantik Toket Pepaya Sangetube Website Tiktok Terabox Pejuang","t_esc":"Zz Bokep Indo Hijab Cantik Toket Pepaya Sangetube Website Tiktok Terabox Pejuang","ln":"00:02:18","sp":"https://wsrv.nl/?url=https%3A//thumbcdn.com/splash/ii7f0yuy2r420h70.jpg","si":"https://wsrv.nl/?url=https%3A//thumbcdn.com/snaps/ii7f0yuy2r420h70.jpg","vw":"1126","vw_fmt":"1.1K","up":"2023-07-26 20:58:20","up_fmt":"26 Jul 2023","up_short":"26 Jul","pg":117}]